silsila/__init__.py
silsila/config.py
silsila/context.py
silsila/mcp_server_registry.py
silsila/py.typed
silsila/agents/__init__.py
silsila/agents/plan_evaluator/__init__.py
silsila/agents/plan_executor/__init__.py
silsila/agents/planner/__init__.py
silsila/cli/__init__.py
silsila/cli/__main__.py
silsila/cli/main.py
silsila/cli/terminal.py
silsila/cli/commands/config.py
silsila/decorators/__init__.py
silsila/eval/__init__.py
silsila/mcp/__init__.py
silsila/mcp/client/__init__.py
silsila/mcp/server/__init__.py
silsila/memory-server/__init__.py
silsila/orchestrator/__init__.py
silsila/prompt_server/__init__.py
silsila/tracing/__init__.py
silsila/workflows/__init__.py
silsila-0.0.1.dist-info/METADATA
silsila-0.0.1.dist-info/WHEEL
silsila-0.0.1.dist-info/entry_points.txt
silsila-0.0.1.dist-info/licenses/LICENSE
silsila-0.0.1.dist-info/RECORD
