Metadata-Version: 2.4
Name: silsila
Version: 0.0.1
Summary: Agent framework for Model Context Protocol (MCP) built on temporal
Author-email: Sarmad Qadri <sarmad@lastmileai.dev>
License:                                  Apache License
License-File: LICENSE
Classifier: License :: OSI Approved :: MIT License
Classifier: Operating System :: OS Independent
Classifier: Programming Language :: Python :: 3
Requires-Python: >=3.10
Requires-Dist: fastapi>=0.115.6
Requires-Dist: instructor>=1.7.0
Requires-Dist: mcp>=1.1.2
Requires-Dist: pydantic>=2.10.4
Requires-Dist: pyyaml>=6.0.2
Requires-Dist: rich>=13.9.4
Requires-Dist: typer>=0.15.1
Provides-Extra: temporal
Requires-Dist: temporalio>=1.8.0; extra == 'temporal'
